adobecli-1.0.data/scripts/commands.py
cat/__init__.py
cat/cat.py
cd/__init__.py
cd/cd.py
cp/__init__.py
cp/cp.py
find/__init__.py
find/find.py
grep/__init__.py
grep/grep.py
head/__init__.py
head/head.py
ls/__init__.py
ls/ls.py
mkdir/__init__.py
mkdir/mkdir.py
mv/__init__.py
mv/mv.py
pwd2/__init__.py
pwd2/pwd.py
rm/__init__.py
rm/rm.py
rmdir/__init__.py
rmdir/rmdir.py
sizeof/__init__.py
sizeof/sizeof.py
tail/__init__.py
tail/tail.py
adobecli-1.0.dist-info/LICENSE
adobecli-1.0.dist-info/METADATA
adobecli-1.0.dist-info/WHEEL
adobecli-1.0.dist-info/top_level.txt
adobecli-1.0.dist-info/RECORD
