Metadata-Version: 2.1
Name: adobecli
Version: 1.0
Summary: A linux-like shell
Home-page: https://git.corp.adobe.com/pragkuma/PY_3
Author: Py-3
Author-email: vaishsha@adobe.com
License: UNKNOWN
Platform: UNKNOWN
Classifier: Programming Language :: Python :: 3
Classifier: License :: OSI Approved :: MIT License
